x509generator
